tests/__init__.py
tests/uprime_tests.py
uprime/__init__.py
uprime/uprime.py
uprime-1.2.dist-info/LICENSE
uprime-1.2.dist-info/METADATA
uprime-1.2.dist-info/WHEEL
uprime-1.2.dist-info/top_level.txt
uprime-1.2.dist-info/RECORD
