Metadata-Version: 2.1
Name: uprime
Version: 1.2
Summary: Automatic control chart calculation and plotting for the u'-chart.
Home-page: https://github.com/Dashlane/uprime
Author: Robert Astel
Author-email: rob.astel@gmail.com
License: Apache License 2.0
Platform: UNKNOWN
Classifier: License :: OSI Approved :: Apache Software License
Classifier: Programming Language :: Python :: 3.4
Classifier: Programming Language :: Python :: 3.5
Classifier: Programming Language :: Python :: 3.6
Classifier: Programming Language :: Python :: 3.7
Requires-Python: >=3.4
Requires-Dist: pandas
Requires-Dist: matplotlib
